obsidian_canvas_python/__init__.py
obsidian_canvas_python/canvas.py
obsidian_canvas_python/core.py
obsidian_canvas_python/enums.py
obsidian_canvas_python/exceptions.py
obsidian_canvas_python/models.py
obsidian_canvas_python/parser.py
obsidian_canvas_python/serializer.py
obsidian_canvas_python/utils.py
obsidian_canvas_python-1.1.dist-info/METADATA
obsidian_canvas_python-1.1.dist-info/WHEEL
obsidian_canvas_python-1.1.dist-info/top_level.txt
obsidian_canvas_python-1.1.dist-info/RECORD
